pytest_tr_api_client/__init__.py
pytest_tr_api_client/service.py
pytest_tr_api_client/test_rail.py
pytest_tr_api_client/validate.py
pytest_tr_api_client-0.3.11.dist-info/METADATA
pytest_tr_api_client-0.3.11.dist-info/WHEEL
pytest_tr_api_client-0.3.11.dist-info/entry_points.txt
pytest_tr_api_client-0.3.11.dist-info/top_level.txt
pytest_tr_api_client-0.3.11.dist-info/RECORD
