Metadata-Version: 2.2
Name: pytest-tr-api-client
Version: 0.3.11
Summary: Pytest hook for custom argument handling and Allure reporting. This plugin allows you to add arguments before running a test.
Author-email: Yevhen Halitsyn <halitsyny@science.regn.net>
License: MIT
